open_irceline/__init__.py
open_irceline/api.py
open_irceline/data.py
open_irceline/forecast.py
open_irceline/rio.py
open_irceline/utils.py
open_irceline-3.0.2.dist-info/LICENSE
open_irceline-3.0.2.dist-info/METADATA
open_irceline-3.0.2.dist-info/WHEEL
open_irceline-3.0.2.dist-info/top_level.txt
open_irceline-3.0.2.dist-info/RECORD
