Metadata-Version: 2.1
Name: open-irceline
Version: 3.0.2
Summary: Get IRCEL - CELINE air quality data 🍃 🇧🇪
Author-email: Jules Dejaeghere <curable.grass491@mailer.me>
License:                                  Apache License
Project-URL: Homepage, https://github.com/jdejaegh/python-irceline
Keywords: air-quality,air,ircel,celine,irceline,open-data,opendata,belgium
Classifier: License :: OSI Approved :: Apache Software License
Classifier: Programming Language :: Python
Classifier: Programming Language :: Python :: 3
Requires-Python: >=3.11
License-File: LICENSE
Requires-Dist: aiohttp>=3.9.5
Requires-Dist: pyproj>=3.6.1
Requires-Dist: async-timeout>=4.0.3
